qf_lib/__init__.py
qf_lib/_version.py
qf_lib/get_sources_root.py
qf_lib/settings.py
qf_lib/starting_dir.py
qf_lib/analysis/__init__.py
qf_lib/analysis/backtests_overfitting/__init__.py
qf_lib/analysis/backtests_overfitting/backtest_overfitting_sheet.py
qf_lib/analysis/backtests_overfitting/minimum_backtest_length.py
qf_lib/analysis/backtests_overfitting/overfitting_analysis.py
qf_lib/analysis/breakout_strength/__init__.py
qf_lib/analysis/breakout_strength/trend_strength.py
qf_lib/analysis/breakout_strength/trend_strength_sheet.py
qf_lib/analysis/common/__init__.py
qf_lib/analysis/common/abstract_document.py
qf_lib/analysis/exposure_analysis/__init__.py
qf_lib/analysis/exposure_analysis/exposure_generator.py
qf_lib/analysis/exposure_analysis/exposure_settings.py
qf_lib/analysis/exposure_analysis/exposure_sheet.py
qf_lib/analysis/model_params_estimation/__init__.py
qf_lib/analysis/model_params_estimation/evaluation_utils.py
qf_lib/analysis/model_params_estimation/model_params_evaluator.py
qf_lib/analysis/rolling_analysis/__init__.py
qf_lib/analysis/rolling_analysis/rolling_analysis.py
qf_lib/analysis/signals_analysis/__init__.py
qf_lib/analysis/signals_analysis/signals_plotter.py
qf_lib/analysis/strategy_monitoring/__init__.py
qf_lib/analysis/strategy_monitoring/assets_monitoring_sheet.py
qf_lib/analysis/strategy_monitoring/pnl_calculator.py
qf_lib/analysis/tearsheets/__init__.py
qf_lib/analysis/tearsheets/abstract_tearsheet.py
qf_lib/analysis/tearsheets/current_positions_sheet.py
qf_lib/analysis/tearsheets/factor_comparison_sheet.py
qf_lib/analysis/tearsheets/portfolio_analysis_sheet.py
qf_lib/analysis/tearsheets/strategy_monitoring_document.py
qf_lib/analysis/tearsheets/tearsheet_comparative.py
qf_lib/analysis/tearsheets/tearsheet_with_benchmark.py
qf_lib/analysis/tearsheets/tearsheet_without_benchmark.py
qf_lib/analysis/timeseries_analysis/__init__.py
qf_lib/analysis/timeseries_analysis/timeseries_analysis.py
qf_lib-4.0.5.dist-info/licenses/LICENSE
qf_lib-4.0.5.dist-info/METADATA
qf_lib-4.0.5.dist-info/WHEEL
qf_lib-4.0.5.dist-info/top_level.txt
qf_lib-4.0.5.dist-info/RECORD
