Metadata-Version: 2.4
Name: qf-lib
Version: 4.0.5
Summary: Quantitative Finance Library
Home-page: https://quarkfin.github.io/qf-lib-info
Author: Jacek Witkowski, Marcin Borratynski, Thomas Ruxton, Dominik Picheta, Olga Kalinowska, Karolina Cynk, Jakub Czerski, Bartlomiej Czajewski, Zeynep Gültuğ Aydemir, Octavian-Mihai Matei, Eirik Thorp Eythorsson, Marek Bais
License: Apache License 2.0
Project-URL: Documentation, https://qf-lib.readthedocs.io
Project-URL: Source, https://github.com/quarkfin/qf-lib
Keywords: quantitative finance backtester
Classifier: Development Status :: 5 - Production/Stable
Classifier: Programming Language :: Python :: 3.12
Classifier: Programming Language :: Python :: 3.11
Classifier: Programming Language :: Python :: 3.10
Classifier: Programming Language :: Python :: 3.9
Classifier: Programming Language :: Python :: 3.8
Classifier: Operating System :: OS Independent
Classifier: Intended Audience :: Science/Research
Classifier: Topic :: Office/Business :: Financial
Classifier: Topic :: Scientific/Engineering :: Information Analysis
Requires-Python: >=3.8.0
License-File: LICENSE
Requires-Dist: pandas<=2.2.3,>=1.4.0
Requires-Dist: xarray<=2024.11.0,>=0.21.0
Requires-Dist: numpy<=1.26.4,>=1.19.3
Requires-Dist: matplotlib<=3.6.1,>=3.4.0
Requires-Dist: Pillow<=10.2.0,>=9.0.0
Requires-Dist: scikit-learn<=1.6.0,>=1.0.0
Requires-Dist: seaborn>=0.11.1
Requires-Dist: openpyxl<=3.1.5,>=3.0.7
Requires-Dist: WeasyPrint==52.5
Requires-Dist: Jinja2<=3.1.4,>=3.0.0
Provides-Extra: documentation
Requires-Dist: autodocsumm==0.2.9; extra == "documentation"
Requires-Dist: sphinx_rtd_theme==1.2.0; extra == "documentation"
Requires-Dist: Sphinx==5.0; extra == "documentation"
Requires-Dist: docutils==0.18.1; extra == "documentation"
Requires-Dist: markupsafe==2.0.1; extra == "documentation"
Provides-Extra: interactive-brokers
Requires-Dist: ibapi; extra == "interactive-brokers"
Provides-Extra: bloomberg-beap-hapi
Requires-Dist: PyJWT<2.0.0,>=0.2.3; extra == "bloomberg-beap-hapi"
Requires-Dist: retrying>=1.3.3; extra == "bloomberg-beap-hapi"
Requires-Dist: beap-lib==0.0.1; extra == "bloomberg-beap-hapi"
Requires-Dist: requests<=2.31.0,>=2.25.1; extra == "bloomberg-beap-hapi"
Provides-Extra: blpapi
Requires-Dist: blpapi<=3.24.4,>=3.21.0; extra == "blpapi"
Provides-Extra: quandl
Requires-Dist: quandl<=3.7.0,>=3.6.1; extra == "quandl"
Provides-Extra: yfinance
Requires-Dist: yfinance>=0.2.55; extra == "yfinance"
Provides-Extra: detailed-analysis
Requires-Dist: statsmodels<0.14.0,>=0.13.0; extra == "detailed-analysis"
Requires-Dist: scipy<1.12.0,>=1.6.3; extra == "detailed-analysis"
Requires-Dist: cvxopt<=1.3.2,>=1.2.7; extra == "detailed-analysis"
Requires-Dist: arch<=7.0,>=5.4; extra == "detailed-analysis"
Provides-Extra: alpaca
Requires-Dist: alpaca-py>=0.37.0; extra == "alpaca"
Dynamic: author
Dynamic: classifier
Dynamic: description
Dynamic: description-content-type
Dynamic: home-page
Dynamic: keywords
Dynamic: license
Dynamic: license-file
Dynamic: project-url
Dynamic: provides-extra
Dynamic: requires-dist
Dynamic: requires-python
Dynamic: summary
